nippoh.py
nippoh-0.0.2.dist-info/DESCRIPTION.rst
nippoh-0.0.2.dist-info/METADATA
nippoh-0.0.2.dist-info/RECORD
nippoh-0.0.2.dist-info/WHEEL
nippoh-0.0.2.dist-info/entry_points.txt
nippoh-0.0.2.dist-info/metadata.json
nippoh-0.0.2.dist-info/top_level.txt
