Metadata-Version: 2.0
Name: nippoh
Version: 0.0.2
Summary: 日報
Home-page: https://bitbucket.org/imagawa_yakata/nippoh
Author: imagawa_yakata(oyakata)
Author-email: imagawa.hougikumaru@gmail.com
License: MIT
Platform: UNKNOWN
